{
  "server_group": "961-980",
  "total_count": 385,
  "data": [
    {
      "uid": 38112449,
      "name": "梦✨东方"
    },
    {
      "uid": 38114188,
      "name": "丶往哪跑（96/7/15，王柯）"
    },
    {
      "uid": 38114799,
      "name": "梦丶振獄"
    },
    {
      "uid": 38115559,
      "name": "无视丶S"
    },
    {
      "uid": 38116602,
      "name": "无视丶阿葵"
    },
    {
      "uid": 38118095,
      "name": "冷"
    },
    {
      "uid": 38118393,
      "name": "梦✨熊猫"
    },
    {
      "uid": 38120564,
      "name": "宇光十色"
    },
    {
      "uid": 38123500,
      "name": "c"
    },
    {
      "uid": 38123831,
      "name": "梦✨荡荡"
    },
    {
      "uid": 38124052,
      "name": "酷酷的小王子"
    },
    {
      "uid": 38124571,
      "name": "无欢"
    },
    {
      "uid": 38125512,
      "name": "吹梦到西洲"
    },
    {
      "uid": 38125628,
      "name": "酷酷的坤宗门"
    },
    {
      "uid": 38127110,
      "name": "相信自己"
    },
    {
      "uid": 38127810,
      "name": "梦✨软兔酒🌸"
    },
    {
      "uid": 38128716,
      "name": "表哥"
    },
    {
      "uid": 38129673,
      "name": "Yuan"
    },
    {
      "uid": 38129846,
      "name": "🚗"
    },
    {
      "uid": 38132171,
      "name": "一个人"
    },
    {
      "uid": 38139644,
      "name": "小王子到处放肆"
    },
    {
      "uid": 38141111,
      "name": "心如颗梦"
    },
    {
      "uid": 38144792,
      "name": "无视丶  聖旨"
    },
    {
      "uid": 38147651,
      "name": "酷酷的小王子"
    },
    {
      "uid": 38148079,
      "name": "因果"
    },
    {
      "uid": 38148189,
      "name": "迪哥"
    },
    {
      "uid": 38149461,
      "name": "饭醉嫌疑人ྈ"
    },
    {
      "uid": 38151244,
      "name": "酷酷的帅王子"
    },
    {
      "uid": 38155110,
      "name": "无视丶抱抱嘉嘉"
    },
    {
      "uid": 38157494,
      "name": "代号九五二七"
    },
    {
      "uid": 38157527,
      "name": "梦✨西红柿🍅"
    },
    {
      "uid": 38160043,
      "name": "梦✨天堂上的仙"
    },
    {
      "uid": 38160290,
      "name": "酷酷的小王子"
    },
    {
      "uid": 38160918,
      "name": "酷酷的小王子"
    },
    {
      "uid": 38162187,
      "name": "长河渐落晓星沉"
    },
    {
      "uid": 38168363,
      "name": "酷酷的小王子"
    },
    {
      "uid": 38168872,
      "name": "法老"
    },
    {
      "uid": 38181011,
      "name": "梦✨岁岁年年"
    },
    {
      "uid": 38181924,
      "name": "梦✨云长"
    },
    {
      "uid": 38183767,
      "name": "无视丶一切"
    },
    {
      "uid": 38185054,
      "name": ">大苦瓜炒蛋<"
    },
    {
      "uid": 38197623,
      "name": "布十戈门"
    },
    {
      "uid": 38200312,
      "name": "酷酷的小王子"
    },
    {
      "uid": 38202930,
      "name": "梦✨AlE"
    },
    {
      "uid": 38202937,
      "name": "神界丨麻秋"
    },
    {
      "uid": 38204698,
      "name": "梦✨香芋派"
    },
    {
      "uid": 38205630,
      "name": "无视丶蟹老板"
    },
    {
      "uid": 38209014,
      "name": "酷酷的小王子"
    },
    {
      "uid": 38211729,
      "name": "梦✨七十二莳"
    },
    {
      "uid": 38213203,
      "name": "酱油"
    },
    {
      "uid": 38216051,
      "name": "清风油炸小林蛙"
    },
    {
      "uid": 38217100,
      "name": "无视丶桃花运来袭"
    },
    {
      "uid": 38218629,
      "name": "七月"
    },
    {
      "uid": 38220986,
      "name": "酷酷的小王子"
    },
    {
      "uid": 38225193,
      "name": "无视丶阿宇"
    },
    {
      "uid": 38226609,
      "name": "一骑浪红尘"
    },
    {
      "uid": 38226639,
      "name": "马户"
    },
    {
      "uid": 38229993,
      "name": "最坏罪名"
    },
    {
      "uid": 38232054,
      "name": "怀沙"
    },
    {
      "uid": 38232407,
      "name": "玫瑰🌹"
    },
    {
      "uid": 38238167,
      "name": "梦✨仙帝"
    },
    {
      "uid": 38243475,
      "name": "梦✨掌心的回忆"
    },
    {
      "uid": 38249060,
      "name": "梦✨五"
    },
    {
      "uid": 38253367,
      "name": "梦✨刀削面"
    },
    {
      "uid": 38257049,
      "name": "十五"
    },
    {
      "uid": 38257875,
      "name": "小猫吃鱼✨✨"
    },
    {
      "uid": 38264141,
      "name": "i18n_728"
    },
    {
      "uid": 38267056,
      "name": "欧乐鉴宝大开门"
    },
    {
      "uid": 38271423,
      "name": "无视丶憧憬"
    },
    {
      "uid": 38271495,
      "name": "小林！"
    },
    {
      "uid": 38272701,
      "name": "风夏"
    },
    {
      "uid": 38273091,
      "name": "梨子"
    },
    {
      "uid": 38274146,
      "name": "啊真"
    },
    {
      "uid": 38277527,
      "name": "清风油炸小黄鱼"
    },
    {
      "uid": 38278248,
      "name": "LEMON"
    },
    {
      "uid": 38280937,
      "name": "清风佛系"
    },
    {
      "uid": 38282459,
      "name": "梦✨燃"
    },
    {
      "uid": 38288940,
      "name": "小椅"
    },
    {
      "uid": 38290490,
      "name": "清风爆炒牛肉粉干"
    },
    {
      "uid": 38292699,
      "name": "无视丶花里胡哨"
    },
    {
      "uid": 38294592,
      "name": "清风白切牛肋条"
    },
    {
      "uid": 38295099,
      "name": "随风"
    },
    {
      "uid": 38298277,
      "name": "纯属娱乐"
    },
    {
      "uid": 38299368,
      "name": "我还会回来的"
    },
    {
      "uid": 38299427,
      "name": "scott"
    },
    {
      "uid": 38299684,
      "name": "梦✨洛神"
    },
    {
      "uid": 38301388,
      "name": "9527"
    },
    {
      "uid": 38305870,
      "name": "江江"
    },
    {
      "uid": 38306768,
      "name": "唐三藏的白嫖之路"
    },
    {
      "uid": 38314006,
      "name": "酷酷的小王子"
    },
    {
      "uid": 38317788,
      "name": "梦✨游戏"
    },
    {
      "uid": 38319702,
      "name": "三七二十一"
    },
    {
      "uid": 38324251,
      "name": "梦✨AA"
    },
    {
      "uid": 38330544,
      "name": "沈阳北的朱清清"
    },
    {
      "uid": 38332701,
      "name": " 梦✨机师"
    },
    {
      "uid": 38332991,
      "name": "黑色翅膀"
    },
    {
      "uid": 38336685,
      "name": "提灯·映桃花"
    },
    {
      "uid": 38337231,
      "name": "梦✨二踢脚"
    },
    {
      "uid": 38345866,
      "name": "群里发腿毛的江"
    },
    {
      "uid": 38349268,
      "name": "😪"
    },
    {
      "uid": 38349908,
      "name": "时间"
    },
    {
      "uid": 38351324,
      "name": "66"
    },
    {
      "uid": 38360716,
      "name": "梦✨秋🍂"
    },
    {
      "uid": 38365020,
      "name": "神界丨明天过后"
    },
    {
      "uid": 38369165,
      "name": "无视、睡不醒"
    },
    {
      "uid": 38370687,
      "name": "NCProf"
    },
    {
      "uid": 38376491,
      "name": "梦✨混沌面"
    },
    {
      "uid": 38377595,
      "name": "梦✨周而复始"
    },
    {
      "uid": 38377667,
      "name": "酸了吧唧"
    },
    {
      "uid": 38378285,
      "name": "无视丶逗腐汝"
    },
    {
      "uid": 38380410,
      "name": "酷酷的小王子"
    },
    {
      "uid": 38383810,
      "name": "梦✨¿¿¿¿¿"
    },
    {
      "uid": 38385174,
      "name": "梦✨Q"
    },
    {
      "uid": 38386354,
      "name": "无视、夜冷"
    },
    {
      "uid": 38386706,
      "name": "无视丶CY"
    },
    {
      "uid": 38386706,
      "name": "cy"
    },
    {
      "uid": 38392845,
      "name": "梦✨；玮"
    },
    {
      "uid": 38398483,
      "name": "流萤舞过夏夜🌌"
    },
    {
      "uid": 38399429,
      "name": "梦✨风霜"
    },
    {
      "uid": 38404596,
      "name": "Beloved"
    },
    {
      "uid": 38406205,
      "name": "无视丶非酋"
    },
    {
      "uid": 38408589,
      "name": "精神病"
    },
    {
      "uid": 38409624,
      "name": "_____十二"
    },
    {
      "uid": 38418278,
      "name": "神界丨静暖岁月"
    },
    {
      "uid": 38419395,
      "name": "曼巴铁肘"
    },
    {
      "uid": 38423699,
      "name": "Ly"
    },
    {
      "uid": 38426871,
      "name": "神界丨孤心"
    },
    {
      "uid": 38434011,
      "name": "因帅关八年"
    },
    {
      "uid": 38434388,
      "name": "别敷衍"
    },
    {
      "uid": 38436161,
      "name": "梦✨手起刀落"
    },
    {
      "uid": 38437578,
      "name": "无视丶小阿鹏"
    },
    {
      "uid": 38438276,
      "name": "神界丨晓风残月"
    },
    {
      "uid": 38439466,
      "name": "拿下！"
    },
    {
      "uid": 38440471,
      "name": "奥视丶夜雨空灵"
    },
    {
      "uid": 38440870,
      "name": "犬来八荒"
    },
    {
      "uid": 38441771,
      "name": "清芙倚玉之荣"
    },
    {
      "uid": 38442247,
      "name": "梦✨下小雨"
    },
    {
      "uid": 38442326,
      "name": "曾经君也折杨柳"
    },
    {
      "uid": 38443389,
      "name": "酷酷的Z王子"
    },
    {
      "uid": 38443724,
      "name": "柒柒"
    },
    {
      "uid": 38443931,
      "name": "梦✨空白"
    },
    {
      "uid": 38444554,
      "name": "无视丶小新"
    },
    {
      "uid": 38444944,
      "name": "清风阁看大门的"
    },
    {
      "uid": 38445783,
      "name": "梦✨"
    },
    {
      "uid": 38447110,
      "name": "红色根据地"
    },
    {
      "uid": 38449506,
      "name": "小先生"
    },
    {
      "uid": 38451030,
      "name": "无视、风绝"
    },
    {
      "uid": 38452782,
      "name": "斯普喷喷"
    },
    {
      "uid": 38453357,
      "name": "甜蜜"
    },
    {
      "uid": 38456239,
      "name": "活磨"
    },
    {
      "uid": 38458317,
      "name": "神界丨我最牛逼"
    },
    {
      "uid": 38458746,
      "name": "单机玩家"
    },
    {
      "uid": 38460952,
      "name": "梦✨提尔"
    },
    {
      "uid": 38461282,
      "name": "无视丶一切（波比）"
    },
    {
      "uid": 38462483,
      "name": "无视、摸鱼懂事"
    },
    {
      "uid": 38467357,
      "name": "月971"
    },
    {
      "uid": 38484225,
      "name": "无视丶阿泽"
    },
    {
      "uid": 38485637,
      "name": "神界丨艾尼"
    },
    {
      "uid": 38485655,
      "name": "无视丶彦祖"
    },
    {
      "uid": 38486947,
      "name": "拂晓"
    },
    {
      "uid": 38487975,
      "name": "无视～天涯蝶舞"
    },
    {
      "uid": 38491768,
      "name": "屮"
    },
    {
      "uid": 38493957,
      "name": "教授"
    },
    {
      "uid": 38496201,
      "name": "摘星破梦"
    },
    {
      "uid": 38496863,
      "name": "梦✨魔法披风"
    },
    {
      "uid": 38496999,
      "name": "无视丶臣"
    },
    {
      "uid": 38499460,
      "name": "智飞风雨7"
    },
    {
      "uid": 38500683,
      "name": "神界~大神官~忆"
    },
    {
      "uid": 38500863,
      "name": "乌拉拉"
    },
    {
      "uid": 38501693,
      "name": "梦✨哲"
    },
    {
      "uid": 38503366,
      "name": "无视丶吴彦祖"
    },
    {
      "uid": 38506149,
      "name": "扶不上墙的蛤蟆"
    },
    {
      "uid": 38522574,
      "name": "冰哥"
    },
    {
      "uid": 38546011,
      "name": "白给"
    },
    {
      "uid": 38548180,
      "name": "梦✨油"
    },
    {
      "uid": 38548886,
      "name": "梦✨长江五号"
    },
    {
      "uid": 38573518,
      "name": "酷酷的小王子"
    },
    {
      "uid": 38574742,
      "name": "清风朗月花正开"
    },
    {
      "uid": 38579490,
      "name": "韩"
    },
    {
      "uid": 38586128,
      "name": "无视973"
    },
    {
      "uid": 38587475,
      "name": "梦✨L"
    },
    {
      "uid": 38588575,
      "name": "c"
    },
    {
      "uid": 38588962,
      "name": "晚点喝可乐"
    },
    {
      "uid": 38589032,
      "name": "a_p"
    },
    {
      "uid": 38594373,
      "name": "梦✨清念"
    },
    {
      "uid": 38595147,
      "name": "apex"
    },
    {
      "uid": 38615715,
      "name": "36岁绝情小姨"
    },
    {
      "uid": 38617293,
      "name": "酷酷的爱慕"
    },
    {
      "uid": 38620190,
      "name": "一梦"
    },
    {
      "uid": 38630380,
      "name": "梦✨雷电錘"
    },
    {
      "uid": 38630717,
      "name": "酷酷的w王子"
    },
    {
      "uid": 38631163,
      "name": "梦✨567"
    },
    {
      "uid": 38632111,
      "name": "斌"
    },
    {
      "uid": 38632334,
      "name": "无视丶过往"
    },
    {
      "uid": 38633019,
      "name": "梦✨琛"
    },
    {
      "uid": 38637084,
      "name": "梦✨Yahweh"
    },
    {
      "uid": 38637169,
      "name": "梦✨修理工"
    },
    {
      "uid": 38637529,
      "name": "无视974"
    },
    {
      "uid": 38638393,
      "name": "清风糖炒小栗子"
    },
    {
      "uid": 38638545,
      "name": "反方向的钟"
    },
    {
      "uid": 38638878,
      "name": "麦麦"
    },
    {
      "uid": 38639547,
      "name": "精彩"
    },
    {
      "uid": 38641708,
      "name": "神界丨背影"
    },
    {
      "uid": 38645386,
      "name": "无视、不会看"
    },
    {
      "uid": 38645943,
      "name": "梦✨煤气罐"
    },
    {
      "uid": 38646047,
      "name": "小赤佬"
    },
    {
      "uid": 38650695,
      "name": "梦✨囤囤鼠"
    },
    {
      "uid": 38652583,
      "name": "海神奈"
    },
    {
      "uid": 38654965,
      "name": "小朱"
    },
    {
      "uid": 38663184,
      "name": "默"
    },
    {
      "uid": 38664637,
      "name": "第二次"
    },
    {
      "uid": 38665419,
      "name": " 雾里"
    },
    {
      "uid": 38665851,
      "name": "随便"
    },
    {
      "uid": 38666631,
      "name": "可可爱爱没有脑袋"
    },
    {
      "uid": 38667732,
      "name": "爱护小动物"
    },
    {
      "uid": 38670254,
      "name": "啊虚真虚"
    },
    {
      "uid": 38671148,
      "name": "饿了"
    },
    {
      "uid": 38672997,
      "name": "酷酷的南瓜头"
    },
    {
      "uid": 38673971,
      "name": "再也不皮了"
    },
    {
      "uid": 38674274,
      "name": "梦✨阿白"
    },
    {
      "uid": 38674371,
      "name": "安和桥"
    },
    {
      "uid": 38676590,
      "name": "$摆烂咸鱼ε"
    },
    {
      "uid": 38676901,
      "name": "0"
    },
    {
      "uid": 38676977,
      "name": "ddddjy"
    },
    {
      "uid": 38678480,
      "name": "ZZ"
    },
    {
      "uid": 38679148,
      "name": "寻觅"
    },
    {
      "uid": 38679753,
      "name": "saber"
    },
    {
      "uid": 38680223,
      "name": "无视、约定"
    },
    {
      "uid": 38680997,
      "name": "无视丶空腹喵"
    },
    {
      "uid": 38681934,
      "name": "钱多多"
    },
    {
      "uid": 38682632,
      "name": "Theshy"
    },
    {
      "uid": 38683071,
      "name": "梦✨日常破防"
    },
    {
      "uid": 38683121,
      "name": "爱在天涯海角💕"
    },
    {
      "uid": 38683427,
      "name": "陈先生"
    },
    {
      "uid": 38683606,
      "name": "保持热爱"
    },
    {
      "uid": 38685031,
      "name": "借口"
    },
    {
      "uid": 38685417,
      "name": "浮白"
    },
    {
      "uid": 38685605,
      "name": "六幻"
    },
    {
      "uid": 38687280,
      "name": "C"
    },
    {
      "uid": 38687482,
      "name": "゛11_"
    },
    {
      "uid": 38692744,
      "name": "酷酷的小王子"
    },
    {
      "uid": 38692989,
      "name": "梦✨哈士奇"
    },
    {
      "uid": 38693080,
      "name": "梦✨欧尼"
    },
    {
      "uid": 38696405,
      "name": "皮一下彦祖咯"
    },
    {
      "uid": 38697810,
      "name": "无1.0"
    },
    {
      "uid": 38698140,
      "name": "梦✨时间"
    },
    {
      "uid": 38699345,
      "name": "乂氼"
    },
    {
      "uid": 38699781,
      "name": "随意"
    },
    {
      "uid": 38701113,
      "name": "吉星·小白白"
    },
    {
      "uid": 38701129,
      "name": "神界142857"
    },
    {
      "uid": 38704903,
      "name": "根本不行先生"
    },
    {
      "uid": 38706807,
      "name": "梦✨白絮"
    },
    {
      "uid": 38708323,
      "name": "南玖"
    },
    {
      "uid": 38712823,
      "name": "🌈 🌈"
    },
    {
      "uid": 38713957,
      "name": "梦✨手擀面"
    },
    {
      "uid": 38714905,
      "name": "夜猫子丶难熬"
    },
    {
      "uid": 38714999,
      "name": "Lukas"
    },
    {
      "uid": 38715431,
      "name": "Esquiver"
    },
    {
      "uid": 38717776,
      "name": "q"
    },
    {
      "uid": 38719927,
      "name": "喜茶"
    },
    {
      "uid": 38720957,
      "name": "无视丶雨秋"
    },
    {
      "uid": 38721120,
      "name": "lei"
    },
    {
      "uid": 38721708,
      "name": "七十七"
    },
    {
      "uid": 38722612,
      "name": "ikun"
    },
    {
      "uid": 38723313,
      "name": "开开门"
    },
    {
      "uid": 38726402,
      "name": "⛅挡不住的H⛅"
    },
    {
      "uid": 38727290,
      "name": "你"
    },
    {
      "uid": 38729830,
      "name": "Mr.李"
    },
    {
      "uid": 38730330,
      "name": "梦✨唁少"
    },
    {
      "uid": 38732469,
      "name": "乐山大佛"
    },
    {
      "uid": 38733989,
      "name": "@梦✨改名"
    },
    {
      "uid": 38735321,
      "name": "赵"
    },
    {
      "uid": 38737576,
      "name": "无视小林的林北"
    },
    {
      "uid": 38738584,
      "name": "纍℡"
    },
    {
      "uid": 38739437,
      "name": "聪聪"
    },
    {
      "uid": 38740096,
      "name": "梦✨温与柔"
    },
    {
      "uid": 38740245,
      "name": "神界丨李"
    },
    {
      "uid": 38740414,
      "name": "奥视丶派大星"
    },
    {
      "uid": 38741913,
      "name": "神界丨蔠嚸"
    },
    {
      "uid": 38742688,
      "name": "义乌小商品直营店"
    },
    {
      "uid": 38744446,
      "name": "沈天泽"
    },
    {
      "uid": 38745706,
      "name": "释若"
    },
    {
      "uid": 38746405,
      "name": "烂软囝仔"
    },
    {
      "uid": 38746944,
      "name": "神界丨顶尖"
    },
    {
      "uid": 38748691,
      "name": "猛猛氪"
    },
    {
      "uid": 38749569,
      "name": "辰风"
    },
    {
      "uid": 38753533,
      "name": "奥视.clove"
    },
    {
      "uid": 38754139,
      "name": " 豪豪"
    },
    {
      "uid": 38754539,
      "name": "邦邦先生～"
    },
    {
      "uid": 38754830,
      "name": "无视978"
    },
    {
      "uid": 38754959,
      "name": "无视977"
    },
    {
      "uid": 38755031,
      "name": "呱唧孤寂"
    },
    {
      "uid": 38755050,
      "name": "zdy"
    },
    {
      "uid": 38755143,
      "name": "🖕"
    },
    {
      "uid": 38755315,
      "name": "酷酷的小王子"
    },
    {
      "uid": 38755573,
      "name": "关键词"
    },
    {
      "uid": 38767892,
      "name": "山野下"
    },
    {
      "uid": 38767911,
      "name": "灰太狼"
    },
    {
      "uid": 38769972,
      "name": "梦✨钓鱼佬"
    },
    {
      "uid": 38770298,
      "name": "梦✨林"
    },
    {
      "uid": 38771224,
      "name": "莫老师"
    },
    {
      "uid": 38771246,
      "name": "夏天"
    },
    {
      "uid": 38774266,
      "name": "老方丈"
    },
    {
      "uid": 38774381,
      "name": "矿战绝带笑"
    },
    {
      "uid": 38780499,
      "name": "最应急之人"
    },
    {
      "uid": 38784736,
      "name": "瑞尔."
    },
    {
      "uid": 38784812,
      "name": "梦✨柚宝"
    },
    {
      "uid": 38785853,
      "name": "简兮"
    },
    {
      "uid": 38786369,
      "name": "太难了"
    },
    {
      "uid": 38786671,
      "name": "󠀀"
    },
    {
      "uid": 38789742,
      "name": "梦✨萧"
    },
    {
      "uid": 38793791,
      "name": "叁贰"
    },
    {
      "uid": 38797030,
      "name": "野良"
    },
    {
      "uid": 38797240,
      "name": "66"
    },
    {
      "uid": 38799426,
      "name": "缪缪"
    },
    {
      "uid": 38800044,
      "name": "安静"
    },
    {
      "uid": 38800666,
      "name": "锦鲤009"
    },
    {
      "uid": 38800916,
      "name": "梦✨无妄子"
    },
    {
      "uid": 38801934,
      "name": "梦✨👻👻"
    },
    {
      "uid": 38808420,
      "name": "梦✨雪"
    },
    {
      "uid": 38811619,
      "name": "差点长成大帅比"
    },
    {
      "uid": 38811625,
      "name": "放荡不羁"
    },
    {
      "uid": 38813473,
      "name": "清风浮沉"
    },
    {
      "uid": 38814198,
      "name": "无视丶悠闲"
    },
    {
      "uid": 38814675,
      "name": "L"
    },
    {
      "uid": 38821901,
      "name": "GP·曦和"
    },
    {
      "uid": 38824741,
      "name": "天蓝"
    },
    {
      "uid": 38828306,
      "name": "慈溪大帝国✨领主"
    },
    {
      "uid": 38849407,
      "name": "无视980"
    },
    {
      "uid": 38888262,
      "name": "无视976"
    },
    {
      "uid": 38888274,
      "name": "无视979"
    },
    {
      "uid": 38951402,
      "name": "酷酷的小王子"
    },
    {
      "uid": 39816074,
      "name": "哄哄"
    },
    {
      "uid": 42261629,
      "name": "酷酷的练习生"
    },
    {
      "uid": 45517260,
      "name": "酷酷的小王子⁴"
    },
    {
      "uid": 60402103,
      "name": "我本善良"
    },
    {
      "uid": 60404331,
      "name": "天气晚来秋"
    },
    {
      "uid": 60409989,
      "name": "老铁很6"
    },
    {
      "uid": 60655532,
      "name": "岁月无声"
    },
    {
      "uid": 60684884,
      "name": "锦鲤no8"
    },
    {
      "uid": 60775507,
      "name": "酷酷的c王子"
    },
    {
      "uid": 60775561,
      "name": "酷酷的y王子"
    },
    {
      "uid": 60809827,
      "name": ":...:·.·"
    },
    {
      "uid": 60883726,
      "name": "向天空飞翔！"
    },
    {
      "uid": 60886233,
      "name": "又一个晚安！"
    },
    {
      "uid": 60889764,
      "name": "猪杂粉"
    },
    {
      "uid": 60962679,
      "name": "赞美太阳"
    },
    {
      "uid": 61628733,
      "name": "随行逛逛！"
    },
    {
      "uid": 65319259,
      "name": "靓仔"
    },
    {
      "uid": 65319483,
      "name": "美男子"
    },
    {
      "uid": 65319724,
      "name": "酷酷的小王子"
    },
    {
      "uid": 65319823,
      "name": "皮皮一号"
    },
    {
      "uid": 65319844,
      "name": "小皮的爸爸"
    },
    {
      "uid": 65319920,
      "name": "酷酷的小王子"
    },
    {
      "uid": 65319972,
      "name": "寻觅1号"
    },
    {
      "uid": 65320030,
      "name": "杜蕾斯2"
    },
    {
      "uid": 65320056,
      "name": "皮皮二号"
    },
    {
      "uid": 65320125,
      "name": "第七次"
    },
    {
      "uid": 65320199,
      "name": "第六次"
    },
    {
      "uid": 65320368,
      "name": "皮皮三号"
    },
    {
      "uid": 65320553,
      "name": "寻🛷"
    },
    {
      "uid": 65320875,
      "name": "皮皮四号"
    },
    {
      "uid": 65321827,
      "name": "苟申"
    },
    {
      "uid": 65321949,
      "name": "蜜雪冰城"
    },
    {
      "uid": 65365111,
      "name": "45658"
    },
    {
      "uid": 65365289,
      "name": "45659"
    },
    {
      "uid": 65365336,
      "name": "45660"
    },
    {
      "uid": 65365368,
      "name": "45661"
    },
    {
      "uid": 65365537,
      "name": "饿了1"
    },
    {
      "uid": 65381665,
      "name": "饿了3"
    },
    {
      "uid": 65381719,
      "name": "饿了2"
    },
    {
      "uid": 65386114,
      "name": "白961"
    },
    {
      "uid": 65386119,
      "name": "酷酷的小王子·"
    },
    {
      "uid": 65411978,
      "name": "甜心宝贝五号"
    },
    {
      "uid": 65413569,
      "name": "(👑"
    },
    {
      "uid": 65413652,
      "name": "♋️♍️"
    },
    {
      "uid": 65413692,
      "name": "i☀️"
    },
    {
      "uid": 65428085,
      "name": "寻思"
    },
    {
      "uid": 65433545,
      "name": "酷酷的小王子"
    },
    {
      "uid": 65435151,
      "name": "白962"
    },
    {
      "uid": 65446630,
      "name": "白963"
    },
    {
      "uid": 65566609,
      "name": "白964"
    },
    {
      "uid": 65645722,
      "name": "爷爷"
    },
    {
      "uid": 65645741,
      "name": "父亲"
    },
    {
      "uid": 65645797,
      "name": "老爸"
    }
  ]
}